[
    {
        "chainId": 1101,
        "name": "Ether",
        "symbol": "ETH",
        "decimals": 18,
        "address": "0x0000000000000000000000000000000000000000",
        "logoURI": "https://wallet-asset.matic.network/img/tokens/eth.svg",
        "tags": ["zkevm", "erc20"],
        "originTokenNetwork": 0,
        "wrappedTokenNetwork": 1,
        "extensions": {
            "rootAddress": "0x0000000000000000000000000000000000000000"
        }
    },
    {
        "chainId": 1101,
        "name": "Matic",
        "symbol": "MATIC",
        "decimals": 18,
        "address": "0xa2036f0538221a77a3937f1379699f44945018d0",
        "logoURI": "https://wallet-asset.matic.network/img/tokens/matic.svg",
        "tags": ["zkevm", "erc20"],
        "originTokenNetwork": 0,
        "wrappedTokenNetwork": 1,
        "extensions": {
            "rootAddress": "0x7d1afa7b718fb893db30a3abc0cfc608aacfebb0"
        }
    },
    {
        "chainId": 1101,
        "name": "USD Coin",
        "symbol": "USDC",
        "decimals": 6,
        "address": "0xa8ce8aee21bc2a48a5ef670afcc9274c7bbbc035",
        "logoURI": "https://wallet-asset.matic.network/img/tokens/usdc.svg",
        "tags": ["zkevm", "stablecoin", "erc20"],
        "originTokenNetwork": 0,
        "wrappedTokenNetwork": 1,
        "extensions": {
            "rootAddress": "0xa0b86991c6218b36c1d19d4a2e9eb0ce3606eb48"
        }
    },
    {
        "chainId": 1101,
        "name": "Tether USD",
        "symbol": "USDT",
        "decimals": 6,
        "address": "0x1e4a5963abfd975d8c9021ce480b42188849d41d",
        "logoURI": "https://wallet-asset.matic.network/img/tokens/usdt.svg",
        "tags": ["zkevm", "stablecoin", "erc20"],
        "originTokenNetwork": 0,
        "wrappedTokenNetwork": 1,
        "extensions": {
            "rootAddress": "0xdac17f958d2ee523a2206206994597c13d831ec7"
        }
    },
    {
        "chainId": 1101,
        "name": "Dai",
        "symbol": "DAI",
        "decimals": 18,
        "address": "0xc5015b9d9161dca7e18e32f6f25c4ad850731fd4",
        "logoURI": "https://wallet-asset.matic.network/img/tokens/dai.svg",
        "tags": ["zkevm", "stablecoin", "erc20"],
        "originTokenNetwork": 0,
        "wrappedTokenNetwork": 1,
        "extensions": {
            "rootAddress": "0x6b175474e89094c44da98b954eedeac495271d0f"
        }
    },
    {
        "chainId": 1101,
        "name": "Aave",
        "symbol": "AAVE",
        "decimals": 18,
        "address": "0x68791cfe079814c46e0e25c19bcc5bfc71a744f7",
        "logoURI": "https://wallet-asset.matic.network/img/tokens/aave.svg",
        "tags": ["zkevm", "erc20"],
        "originTokenNetwork": 0,
        "wrappedTokenNetwork": 1,
        "extensions": {
            "rootAddress": "0x7fc66500c84a76ad7e9c93437bfc5ac33e2ddae9"
        }
    },
    {
        "chainId": 1101,
        "name": "ChainLink Token",
        "symbol": "LINK",
        "decimals": 18,
        "address": "0x4b16e4752711a7abec32799c976f3cefc0111f2b",
        "logoURI": "https://wallet-asset.matic.network/img/tokens/link.svg",
        "tags": ["zkevm", "erc20"],
        "originTokenNetwork": 0,
        "wrappedTokenNetwork": 1,
        "extensions": {
            "rootAddress": "0x514910771AF9Ca656af840dff83E8264EcF986CA"
        }
    },
    {
        "chainId": 1101,
        "name": "Wrapped BTC",
        "symbol": "WBTC",
        "decimals": 8,
        "address": "0xea034fb02eb1808c2cc3adbc15f447b93cbe08e1",
        "logoURI": "https://wallet-asset.matic.network/img/tokens/wbtc.svg",
        "tags": ["zkevm", "erc20"],
        "originTokenNetwork": 0,
        "wrappedTokenNetwork": 1,
        "extensions": {
            "rootAddress": "0x2260fac5e5542a773aa44fbcfedf7c193bc2c599"
        }
    },
    {
        "chainId": 1101,
        "name": "Uniswap",
        "symbol": "UNI",
        "decimals": 18,
        "address": "0x2548c94a3092494db3af864cc2cf781a72f55678",
        "logoURI": "https://wallet-asset.matic.network/img/tokens/uni.svg",
        "tags": ["zkevm", "erc20"],
        "originTokenNetwork": 0,
        "wrappedTokenNetwork": 1,
        "extensions": {
            "rootAddress": "0x1f9840a85d5af5bf1d1762f925bdaddc4201f984"
        }
    },
    {
        "chainId": 1101,
        "name": "Balancer",
        "symbol": "BAL",
        "decimals": 18,
        "address": "0x120ef59b80774f02211563834d8e3b72cb1649d6",
        "logoURI": "https://wallet-asset.matic.network/img/tokens/bal.svg",
        "tags": ["zkevm", "erc20"],
        "originTokenNetwork": 0,
        "wrappedTokenNetwork": 1,
        "extensions": {
            "rootAddress": "0xba100000625a3754423978a60c9317c58a424e3d"
        }
    },
    {
        "chainId": 1101,
        "name": "Staked MATIC",
        "symbol": "stMATIC",
        "decimals": 18,
        "address": "0x83b874c1e09d316059d929da402dcb1a98e92082",
        "logoURI": "https://s2.coinmarketcap.com/static/img/coins/64x64/18688.png",
        "tags": ["zkevm", "erc20"],
        "originTokenNetwork": 0,
        "wrappedTokenNetwork": 1,
        "extensions": {
            "rootAddress": "0x9ee91f9f426fa633d227f7a9b000e28b9dfd8599"
        }
    },
    {
        "chainId": 1101,
        "name": "Curve DAO Token",
        "symbol": "CRV",
        "decimals": 18,
        "address": "0x3d5320821bfca19fb0b5428f2c79d63bd5246f89",
        "tags": ["zkevm", "erc20"],
        "logoURI": "https://wallet-asset.matic.network/img/tokens/crv.svg",
        "originTokenNetwork": 0,
        "wrappedTokenNetwork": 1,
        "extensions": {
            "rootAddress": "0xd533a949740bb3306d119cc777fa900ba034cd52"
        }
    },
    {
        "chainId": 1101,
        "name": "Lido DAO Token",
        "symbol": "LDO",
        "decimals": 18,
        "address": "0x7e2feea957b7d1606335e339754f4e52b452b792",
        "tags": ["zkevm", "erc20"],
        "logoURI": "https://s2.coinmarketcap.com/static/img/coins/64x64/8000.png",
        "originTokenNetwork": 0,
        "wrappedTokenNetwork": 1,
        "extensions": {
            "rootAddress": "0x5A98FcBEA516Cf06857215779Fd812CA3beF1B32"
        }
    },
    {
        "chainId": 1101,
        "name": "Liquid Staked Matic by Stader",
        "symbol": "MaticX",
        "decimals": 18,
        "address": "0xf9ed88937b2d82707d0eabd8c3d9aa4870b714d3",
        "logoURI": "https://user-images.githubusercontent.com/19915413/198746681-bcfd16fd-72e5-41b3-bcb8-5494d77195e0.svg",
        "tags": ["zkevm", "erc20"],
        "originTokenNetwork": 0,
        "wrappedTokenNetwork": 1,
        "extensions": {
            "rootAddress": "0xf03a7eb46d01d9ecaa104558c732cf82f6b6b645"
        }
    },
    {
        "chainId": 1101,
        "name": "Wrapped Ether",
        "symbol": "WETH",
        "decimals": 18,
        "address": "0xb584516c8d90f133A48af5cC445cc5d924cf9863",
        "logoURI": "https://wallet-asset.matic.network/img/tokens/weth.svg",
        "tags": ["zkevm", "erc20", "noDeposit", "noWithdraw"],
        "originTokenNetwork": 0,
        "wrappedTokenNetwork": 1,
        "extensions": {
            "rootAddress": "0xC02aaA39b223FE8D0A0e5C4F27eAD9083C756Cc2"
        }
    },
    {
        "chainId": 1101,
        "name": "Wrapped Ether",
        "symbol": "WETH",
        "decimals": 18,
        "address": "0x4F9A0e7FD2Bf6067db6994CF12E4495Df938E6e9",
        "logoURI": "https://wallet-asset.matic.network/img/tokens/weth.svg",
        "tags": ["zkevm", "erc20", "noDeposit", "noWithdraw"],
        "originTokenNetwork": 1,
        "wrappedTokenNetwork": 0,
        "extensions": {
            "rootAddress": "0x140dAa3085f156921D5B148aa108225Cc066457C"
        }
    },
    {
        "chainId": 1101,
        "name": "Frax Share",
        "symbol": "FXS",
        "decimals": 18,
        "address": "0x7940DEAe60FA6dBB56dE469dFCdDc84D2B6b17EA",
        "logoURI": "https://wallet-asset.matic.network/img/tokens/fxs.svg",
        "tags": ["zkevm", "erc20", "noDeposit", "noWithdraw"],
        "originTokenNetwork": 0,
        "wrappedTokenNetwork": 1,
        "extensions": {
            "rootAddress": "0x3432b6a60d23ca0dfca7761b7ab56459d9c964d0"
        }
    },
    {
        "chainId": 1101,
        "name": "Frax Share",
        "symbol": "FXS",
        "decimals": 18,
        "address": "0x6b856a14CeA1d7dCfaF80fA6936c0b75972cCacE",
        "logoURI": "https://wallet-asset.matic.network/img/tokens/fxs.svg",
        "tags": ["zkevm", "erc20", "noDeposit", "noWithdraw"],
        "originTokenNetwork": 1,
        "wrappedTokenNetwork": 0,
        "extensions": {
            "rootAddress": "0x1dc846D626E0DdDF983d7f269E7C8E7C3D4050dC"
        }
    },
    {
        "chainId": 1101,
        "name": "Frax Ether",
        "symbol": "frxETH",
        "decimals": 18,
        "address": "0x3e7BD82b7DBCe275fF86ff419d8BdF37b05e574B",
        "logoURI": "https://etherscan.io/token/images/fraxethcanonical2_32.png",
        "tags": ["zkevm", "erc20", "noDeposit", "noWithdraw"],
        "originTokenNetwork": 0,
        "wrappedTokenNetwork": 1,
        "extensions": {
            "rootAddress": "0x5e8422345238f34275888049021821e8e08caa1f"
        }
    },
    {
        "chainId": 1101,
        "name": "Frax Ether",
        "symbol": "frxETH",
        "decimals": 18,
        "address": "0xcf7ecee185f19e2e970a301ee37f93536ed66179",
        "logoURI": "https://etherscan.io/token/images/fraxethcanonical2_32.png",
        "tags": ["zkevm", "erc20", "noDeposit", "noWithdraw"],
        "originTokenNetwork": 1,
        "wrappedTokenNetwork": 0,
        "extensions": {
            "rootAddress": "0xD4bEE4BEc9306994AfEB6EC8d9484dcb5ad71bDD"
        }
    },
    {
        "chainId": 1101,
        "name": "Staked Frax Ether",
        "symbol": "sfrxETH",
        "decimals": 18,
        "address": "0x595157F1ba7FB5bECcFD689659d3C343319F533e",
        "logoURI": "https://etherscan.io/token/images/sfrxeth2_32.png",
        "tags": ["zkevm", "erc20", "noDeposit", "noWithdraw"],
        "originTokenNetwork": 0,
        "wrappedTokenNetwork": 1,
        "extensions": {
            "rootAddress": "0xac3E018457B222d93114458476f3E3416Abbe38F"
        }
    },
    {
        "chainId": 1101,
        "name": "Staked Frax Ether",
        "symbol": "sfrxETH",
        "decimals": 18,
        "address": "0x7c2af1fb79d0b1c67d4eb802d44c673d0a1d2c04",
        "logoURI": "https://etherscan.io/token/images/sfrxeth2_32.png",
        "tags": ["zkevm", "erc20", "noDeposit", "noWithdraw"],
        "originTokenNetwork": 1,
        "wrappedTokenNetwork": 0,
        "extensions": {
            "rootAddress": "0x03279b85f18Ea904d55628d9F45b8D7ea4201B18"
        }
    },
    {
        "chainId": 1101,
        "name": "Frax Price Index",
        "symbol": "FPI",
        "decimals": 18,
        "address": "0xE765a819dbEfDEC134DB20F0b82a2F3F13a5cd4a",
        "logoURI": "https://etherscan.io/token/images/fraxprice_32.png",
        "tags": ["zkevm", "erc20", "noDeposit", "noWithdraw"],
        "originTokenNetwork": 0,
        "wrappedTokenNetwork": 1,
        "extensions": {
            "rootAddress": "0x5ca135cb8527d76e932f34b5145575f9d8cbe08e"
        }
    },
    {
        "chainId": 1101,
        "name": "Frax Price Index",
        "symbol": "FPI",
        "decimals": 18,
        "address": "0x7c2af1fb79d0b1c67d4eb802d44c673d0a1d2c04",
        "logoURI": "https://etherscan.io/token/images/fraxprice_32.png",
        "tags": ["zkevm", "erc20", "noDeposit", "noWithdraw"],
        "originTokenNetwork": 1,
        "wrappedTokenNetwork": 0,
        "extensions": {
            "rootAddress": "0x2b684D1BAb13A547CD196Ca6168d59509D9e9b37"
        }
    },
    {
        "chainId": 1101,
        "name": "Frax Price Index",
        "symbol": "FPI",
        "decimals": 18,
        "address": "0x2b684D1BAb13A547CD196Ca6168d59509D9e9b37",
        "logoURI": "https://etherscan.io/token/images/fraxpriceshare_32.png",
        "tags": ["zkevm", "erc20", "noDeposit", "noWithdraw"],
        "originTokenNetwork": 0,
        "wrappedTokenNetwork": 1,
        "extensions": {
            "rootAddress": "0xc2544a32872a91f4a553b404c6950e89de901fdb"
        }
    },
    {
        "chainId": 1101,
        "name": "Frax Price Index",
        "symbol": "FPI",
        "decimals": 18,
        "address": "0xdE7df9036801676aF0cB73661d93a098c0085fba",
        "logoURI": "https://etherscan.io/token/images/fraxpriceshare_32.png",
        "tags": ["zkevm", "erc20", "noDeposit", "noWithdraw"],
        "originTokenNetwork": 1,
        "wrappedTokenNetwork": 0,
        "extensions": {
            "rootAddress": "0xfF8f4fd427EDc035ea840Ff2A6b956AFA2eC0951"
        }
    }
]
